LICENSE
MANIFEST.in
README.rst
setup.cfg
setup.py
django_oscar_paypal_fork_b74153f.egg-info/PKG-INFO
django_oscar_paypal_fork_b74153f.egg-info/SOURCES.txt
django_oscar_paypal_fork_b74153f.egg-info/dependency_links.txt
django_oscar_paypal_fork_b74153f.egg-info/requires.txt
django_oscar_paypal_fork_b74153f.egg-info/top_level.txt
paypal/__init__.py
paypal/admin.py
paypal/base.py
paypal/exceptions.py
paypal/gateway.py
paypal/models.py
paypal/express/__init__.py
paypal/express/admin.py
paypal/express/exceptions.py
paypal/express/facade.py
paypal/express/gateway.py
paypal/express/models.py
paypal/express/urls.py
paypal/express/views.py
paypal/express/dashboard/__init__.py
paypal/express/dashboard/app.py
paypal/express/dashboard/views.py
paypal/payflow/__init__.py
paypal/payflow/admin.py
paypal/payflow/codes.py
paypal/payflow/facade.py
paypal/payflow/gateway.py
paypal/payflow/models.py
paypal/payflow/dashboard/__init__.py
paypal/payflow/dashboard/app.py
paypal/payflow/dashboard/views.py
paypal/templates/paypal/express/preview.html
paypal/templates/paypal/express/dashboard/transaction_detail.html
paypal/templates/paypal/express/dashboard/transaction_list.html
paypal/templates/paypal/payflow/transaction_detail.html
paypal/templates/paypal/payflow/transaction_list.html