Metadata-Version: 1.1
Name: django-oscar-paypal-fork-b74153f
Version: 0.9.5
Summary: Integration with PayPal Express, PayPal Payflow Pro and Adaptive Payments for django-oscar
Home-page: https://github.com/tangentlabs/django-oscar-paypal
Author: David Winterbottom
Author-email: david.winterbottom@tangentlabs.co.uk
License: Copyright (c) 2011, Tangent Communications PLC and individual contributors.
